mlperf_loadgen.cp312-win32.pyd
mlcommons_loadgen/__init__.py
mlcommons_loadgen/version_generator.py
mlcommons_loadgen-6.0.4.dist-info/METADATA
mlcommons_loadgen-6.0.4.dist-info/WHEEL
mlcommons_loadgen-6.0.4.dist-info/top_level.txt
mlcommons_loadgen-6.0.4.dist-info/RECORD
