Metadata-Version: 2.1
Name: mlcommons_loadgen
Version: 6.0.4
Summary: MLPerf Inference LoadGen python bindings
Home-page: https://mlcommons.org/
